timer/__init__.py
timer/__init__.pyi
timer4-1.1.0.dist-info/LICENSE
timer4-1.1.0.dist-info/METADATA
timer4-1.1.0.dist-info/WHEEL
timer4-1.1.0.dist-info/RECORD
