Metadata-Version: 2.1
Name: timer4
Version: 1.1.0
Summary: Timing Python code made easy
License: MIT
Author: Binh Vu
Author-email: binh@toan2.com
Requires-Python: >=3.7,<4.0
Classifier: License :: OSI Approved :: MIT License
Classifier: Programming Language :: Python :: 3
Classifier: Programming Language :: Python :: 3.7
Classifier: Programming Language :: Python :: 3.8
Classifier: Programming Language :: Python :: 3.9
Classifier: Programming Language :: Python :: 3.10
Classifier: Programming Language :: Python :: 3.11
